django_server_autoreload/Django_AutoReloader.py
django_server_autoreload/__init__.py
django_server_autoreload-1.4.6.dist-info/LICENSE.txt
django_server_autoreload-1.4.6.dist-info/METADATA
django_server_autoreload-1.4.6.dist-info/WHEEL
django_server_autoreload-1.4.6.dist-info/top_level.txt
django_server_autoreload-1.4.6.dist-info/RECORD
