Metadata-Version: 2.1
Name: django-server-autoreload
Version: 1.4.6
Summary: Python Package for Reloading Django Server at some specific time once every day,Note: this package only works in django installed in windows os. 
Home-page: https://github.com/odiwuorlameck2019gmail
Author: Odiwuor Lameck
Author-email: odiwuorlameck2019@gmail.com
License: MIT
Platform: UNKNOWN
Classifier: License :: OSI Approved :: MIT License
Classifier: Programming Language :: Python
Classifier: Programming Language :: Python :: 3
Classifier: Programming Language :: Python :: 3.6
Classifier: Programming Language :: Python :: Implementation :: CPython
Classifier: Programming Language :: Python :: Implementation :: PyPy
Requires-Python: >=3.6.0
License-File: LICENSE.txt
Requires-Dist: psutil
Requires-Dist: schedule
